{
    "version": "0.4",
    "title": "404",
    "type": "error-404",
    "metadata": {
        "template_type": "single-404",
        "include_in_zip": "1",
        "elementor_pro_required": "1",
        "elementor_library_type": "error-404",
        "elementor_pro_conditions": [
            "include\/singular\/not_found404"
        ],
        "additional_template_information": [
            "This is a \"Error 404\" template for Elementor Pro.",
            "This template will display on: 404 Page."
        ],
        "wp_page_template": "default"
    },
    "content": [
        {
            "id": "5b01bd00",
            "settings": {
                "content_width": {
                    "unit": "px",
                    "size": 1440,
                    "sizes": []
                },
                "structure": "20",
                "padding": {
                    "unit": "px",
                    "top": "200",
                    "right": "50",
                    "bottom": "0",
                    "left": "50",
                    "isLinked": false
                },
                "padding_tablet": {
                    "unit": "px",
                    "top": "250",
                    "right": "15",
                    "bottom": "0",
                    "left": "15",
                    "isLinked": false
                },
                "background_background": "classic",
                "background_image": {
                    "url": "https:\/\/kit.wirastudio.co\/singsong\/wp-content\/uploads\/sites\/30\/2022\/03\/dance-club.jpg",
                    "id": 109,
                    "alt": "Dance club",
                    "source": "library"
                },
                "background_position": "center center",
                "background_attachment": "fixed",
                "background_size": "cover",
                "background_overlay_background": "classic",
                "background_overlay_color": "#000000",
                "background_overlay_opacity": {
                    "unit": "px",
                    "size": 0.65000000000000002220446049250313080847263336181640625,
                    "sizes": []
                },
                "reverse_order_tablet": "reverse-tablet",
                "reverse_order_mobile": "reverse-mobile"
            },
            "elements": [
                {
                    "id": "651b5d5f",
                    "settings": {
                        "_column_size": 50,
                        "_inline_size": null,
                        "_inline_size_tablet": 100,
                        "padding": {
                            "unit": "px",
                            "top": "100",
                            "right": "25",
                            "bottom": "100",
                            "left": "0",
                            "isLinked": false
                        },
                        "padding_tablet": {
                            "unit": "px",
                            "top": "25",
                            "right": "0",
                            "bottom": "0",
                            "left": "0",
                            "isLinked": false
                        }
                    },
                    "elements": [
                        {
                            "id": "22b225f9",
                            "settings": {
                                "title": "Something Is Wrong",
                                "header_size": "span",
                                "__globals__": {
                                    "title_color": "globals\/colors?id=primary",
                                    "typography_typography": "globals\/typography?id=accent"
                                }
                            },
                            "elements": [],
                            "isInner": false,
                            "widgetType": "heading",
                            "elType": "widget"
                        },
                        {
                            "id": "778c33d4",
                            "settings": {
                                "selected_icon": {
                                    "value": "fas fa-square-full",
                                    "library": "fa-solid"
                                },
                                "align": "left",
                                "size": {
                                    "unit": "px",
                                    "size": 90,
                                    "sizes": []
                                },
                                "_transform_rotate_popover": "transform",
                                "_transform_rotateZ_effect": {
                                    "unit": "px",
                                    "size": 20,
                                    "sizes": []
                                },
                                "_element_width": "auto",
                                "__globals__": {
                                    "primary_color": "globals\/colors?id=secondary"
                                }
                            },
                            "elements": [],
                            "isInner": false,
                            "widgetType": "icon",
                            "elType": "widget"
                        },
                        {
                            "id": "4ac9cdbb",
                            "settings": {
                                "selected_icon": {
                                    "value": "fas fa-square-full",
                                    "library": "fa-solid"
                                },
                                "align": "left",
                                "size": {
                                    "unit": "px",
                                    "size": 90,
                                    "sizes": []
                                },
                                "_margin": {
                                    "unit": "px",
                                    "top": "25",
                                    "right": "0",
                                    "bottom": "0",
                                    "left": "-65",
                                    "isLinked": false
                                },
                                "_transform_rotate_popover": "transform",
                                "_transform_rotateZ_effect": {
                                    "unit": "px",
                                    "size": 20,
                                    "sizes": []
                                },
                                "_element_width": "auto",
                                "__globals__": {
                                    "primary_color": "globals\/colors?id=7f20f40"
                                },
                                "_margin_mobile": {
                                    "unit": "px",
                                    "top": "25",
                                    "right": "0",
                                    "bottom": "-100",
                                    "left": "-65",
                                    "isLinked": false
                                }
                            },
                            "elements": [],
                            "isInner": false,
                            "widgetType": "icon",
                            "elType": "widget"
                        },
                        {
                            "id": "9731e3a",
                            "settings": {
                                "title": "Page Not Found",
                                "header_size": "h1",
                                "_margin": {
                                    "unit": "%",
                                    "top": "-15",
                                    "right": "0",
                                    "bottom": "0",
                                    "left": "0",
                                    "isLinked": false
                                },
                                "_margin_tablet": {
                                    "unit": "%",
                                    "top": "",
                                    "right": "",
                                    "bottom": "",
                                    "left": "",
                                    "isLinked": true
                                },
                                "_margin_mobile": {
                                    "unit": "%",
                                    "top": "-30",
                                    "right": "0",
                                    "bottom": "0",
                                    "left": "0",
                                    "isLinked": false
                                },
                                "__dynamic__": []
                            },
                            "elements": [],
                            "isInner": false,
                            "widgetType": "heading",
                            "elType": "widget"
                        },
                        {
                            "id": "237389e6",
                            "settings": {
                                "_margin_tablet": {
                                    "unit": "px",
                                    "top": "-50",
                                    "right": "0",
                                    "bottom": "0",
                                    "left": "0",
                                    "isLinked": false
                                },
                                "_margin_mobile": {
                                    "unit": "px",
                                    "top": "-50",
                                    "right": "0",
                                    "bottom": "0",
                                    "left": "0",
                                    "isLinked": false
                                }
                            },
                            "elements": [],
                            "isInner": false,
                            "widgetType": "text-editor",
                            "elType": "widget"
                        },
                        {
                            "id": "2302f885",
                            "settings": {
                                "placeholder": "Search...",
                                "button_text": "Search",
                                "size": {
                                    "unit": "px",
                                    "size": 75,
                                    "sizes": []
                                },
                                "border_radius": {
                                    "unit": "px",
                                    "size": 0,
                                    "sizes": []
                                },
                                "button_text_color": "#FFFFFF",
                                "button_text_color_hover": "#FFFFFF",
                                "__globals__": {
                                    "input_background_color": "globals\/colors?id=50b2a21",
                                    "button_background_color": "globals\/colors?id=primary",
                                    "button_background_color_hover": "globals\/colors?id=secondary"
                                }
                            },
                            "elements": [],
                            "isInner": false,
                            "widgetType": "search-form",
                            "elType": "widget"
                        }
                    ],
                    "isInner": false,
                    "elType": "column"
                },
                {
                    "id": "68f95398",
                    "settings": {
                        "_column_size": 50,
                        "_inline_size": null,
                        "_inline_size_tablet": 100,
                        "padding": {
                            "unit": "px",
                            "top": "0",
                            "right": "0",
                            "bottom": "0",
                            "left": "25",
                            "isLinked": false
                        },
                        "padding_tablet": {
                            "unit": "px",
                            "top": "0",
                            "right": "0",
                            "bottom": "0",
                            "left": "0",
                            "isLinked": false
                        },
                        "content_position": "center"
                    },
                    "elements": [
                        {
                            "id": "2ea14db8",
                            "settings": {
                                "title": "404",
                                "align": "center",
                                "__globals__": {
                                    "typography_typography": "globals\/typography?id=5898891",
                                    "title_color": "globals\/colors?id=primary"
                                }
                            },
                            "elements": [],
                            "isInner": false,
                            "widgetType": "heading",
                            "elType": "widget"
                        }
                    ],
                    "isInner": false,
                    "elType": "column"
                }
            ],
            "isInner": false,
            "elType": "section"
        }
    ]
}